satmetrix/__init__.py
satmetrix/exceptions.py
satmetrix-0.0.8.dist-info/DESCRIPTION.rst
satmetrix-0.0.8.dist-info/METADATA
satmetrix-0.0.8.dist-info/RECORD
satmetrix-0.0.8.dist-info/WHEEL
satmetrix-0.0.8.dist-info/metadata.json
satmetrix-0.0.8.dist-info/top_level.txt
