Metadata-Version: 2.0
Name: satmetrix
Version: 0.0.8
Summary: Satmetrix
Home-page: https://github.com/blade2005/satmetrix
Author: Craig Davis
Author-email: cdavis@alertlogic.com
License: GPLv3
Keywords: satmetrix
Platform: UNKNOWN
Classifier: Development Status :: 3 - Alpha
Classifier: Intended Audience :: Developers
Classifier: Topic :: Software Development :: Build Tools
Classifier: License :: OSI Approved :: GNU General Public License v3 (GPLv3)
Classifier: Programming Language :: Python :: 2
Classifier: Programming Language :: Python :: 2.7
Requires-Dist: hammock
